Lab8/exp8_fsm/mealy/top.sv
`default_nettype none
// Empty top module

module top (
  // I/O ports
  input  logic hz100, reset,
  input  logic [20:0] pb,
  output logic [7:0] left, right,
         ss7, ss6, ss5, ss4, ss3, ss2, ss1, ss0,
  output logic red, green, blue,

  // UART ports
  output logic [7:0] txdata,
  input  logic [7:0] rxdata,
  output logic txclk, rxclk,
  input  logic txready, rxready
);

endmodule

// mealy machine to detect 1101 pattern
module mealy(
  input logic clk, n_rst, i, 
  output logic o
);
  
typedef enum {S0,S1,S2,S3} FSM;
FSM state;


always_ff @(posedge clk or negedge n_rst)
  if (!n_rst) begin
    state <= S0;
    o <= 0;
  end
  else begin
    case (state)
      S0: state <= (i) ? S1 : S0;
      S1: state <= (i) ? S2 : S0;
      S2: state <= (i) ? S2 : S3;
      S3: state <= (i) ? S1 : S0;
      default: state <= S0;
    endcase
  o <= (state == S3 && i);
  end
  
endmodule

//patterncount

Lab8/exp8_fsm/mealy/tb.sv
//ADD YOUR TESTCASES AT BOTTOM

module lab_testbench ();

logic CLK, N_RST, I, O;

mealy u1 (.clk(CLK), .n_rst(N_RST), .i(I), .o(O));
logic [1023:0] testname;

task automatic clock(integer n);
    while (n != 0) begin
        CLK = 1'b1;
        #1;
        CLK = 1'b0;
        #1;
        n--;
    end
endtask //automatic clk

initial begin
    $dumpfile ("mealy.vcd");
    $dumpvars (0, lab_testbench);
    
    testname="first test with N_RST value 0";
    I = 1'b1; N_RST = 1'b0; CLK = 1'b0;
clock(1);
    #0.25;
    testname="random test1 with N_RST high";
    I = 1'b0; N_RST = 1'b1; CLK=1'b1;
clock(1);
    #0.25;
    testname="random test2 with N_RST high";
    I = 1'b1; N_RST = 1'b1;
clock(1);
    #0.25;
    testname="random test3 with N_RST high";
   I = 1'b1; N_RST = 1'b1;
clock(1);
    #0.25;
   testname="random test4 with N_RST high";
    I = 1'b0; N_RST = 1'b1;
clock(1);
    #0.25;
    testname="random test5 with N_RST high";
    I = 1'b1; N_RST = 1'b1;
clock(1);
// add your test cases here
end
endmodule

Lab8/exp8_fsm/mealy/mealy.vcd
$date
	Wed Jun  7 14:32:21 2023
$end
$version
	Icarus Verilog
$end
$timescale
	1s
$end
$scope module lab_testbench $end
$var wire 1 ! O $end
$var reg 1 " CLK $end
$var reg 1 # I $end
$var reg 1 $ N_RST $end
$var reg 1024 % testname [1023:0] $end
$scope module u1 $end
$var wire 1 " clk $end
$var wire 1 # i $end
$var wire 1 $ n_rst $end
$var reg 1 ! o $end
$var integer 32 & state [31:0] $end
$upscope $end
$scope task clock $end
$upscope $end
$upscope $end
$enddefinitions $end
$comment Show the parameter values. $end
$dumpall
$end
#0
$dumpvars
b0 &
b110011001101001011100100111001101110100001000000111010001100101011100110111010000100000011101110110100101110100011010000010000001001110010111110101001001010011010101000010000001110110011000010110110001110101011001010010000000110000 %
0$
1#
1"
0!
$end
#1
0"
#2
1"
1$
0#
b1110010011000010110111001100100011011110110110100100000011101000110010101110011011101000011000100100000011101110110100101110100011010000010000001001110010111110101001001010011010101000010000001101000011010010110011101101000 %
#3
0"
#4
b1 &
1"
1#
b1110010011000010110111001100100011011110110110100100000011101000110010101110011011101000011001000100000011101110110100101110100011010000010000001001110010111110101001001010011010101000010000001101000011010010110011101101000 %
#5
0"
#6
b10 &
1"
b1110010011000010110111001100100011011110110110100100000011101000110010101110011011101000011001100100000011101110110100101110100011010000010000001001110010111110101001001010011010101000010000001101000011010010110011101101000 %
#7
0"
#8
b11 &
1"
0#
b1110010011000010110111001100100011011110110110100100000011101000110010101110011011101000011010000100000011101110110100101110100011010000010000001001110010111110101001001010011010101000010000001101000011010010110011101101000 %
#9
0"
#10
1!
b1 &
1"
1#
b1110010011000010110111001100100011011110110110100100000011101000110010101110011011101000011010100100000011101110110100101110100011010000010000001001110010111110101001001010011010101000010000001101000011010010110011101101000 %
#11
0"
#12
0!
b10 &
1"
b1110100011001010111001101110100001000000110001101100001011100110110010100100000011001100110111101110010001000000011000100110001001100000011000100110001001100000011000100110001001100000011000100110000 %
#13
0"
#14
1"
#15
0"
#16
b11 &
1"
0#
#17
0"
#18
1!
b1 &
1"
1#
#19
0"
#20
0!
b10 &
1"
#21
0"
#22
b11 &
1"
0#
#23
0"
#24
1!
b1 &
1"
1#
#25
0"
#26
0!
b10 &
1"
#27
0"
#28
b11 &
1"
0#
#29
0"
#30
1!
b1 &
1"
1#
#31
0"
#32
0!
b0 &
1"
0#
