Lab7a/top.sv
`default_nettype none

module top (
  // I/O ports
  input  logic hz100, reset,
  input  logic [20:0] pb,
  output logic [7:0] left, right,
         ss7, ss6, ss5, ss4, ss3, ss2, ss1, ss0,
  output logic red, green, blue,

  // UART ports
  output logic [7:0] txdata,
  input  logic [7:0] rxdata,
  output logic txclk, rxclk,
  input  logic txready, rxready
);

//task 1
d_ff u1(.clk(hz100), .n_rst(pb[0]), .d_in(pb[1]), .d_out(right[0]));

//task 1.5
jk_ff u3(.clk(hz100), .n_rst(pb[0]), .j_in(pb[1]), .k_in(pb[2]), .q_out(right[2]));

//task 2
sync_low u2(.clk(hz100), .n_rst(pb[0]), .async_in(pb[1]), .sync_out(right[1]));
endmodule

//dflipflop
module d_ff(
  input logic clk, n_rst, d_in,
  output logic d_out
);

always_ff @(posedge clk, negedge n_rst)
  if (!n_rst)
    d_out <= 1'b0;
  else
    d_out <= d_in;
endmodule

//2-bit synchronizer
module sync_low(
  input logic clk, n_rst, async_in,
  output logic sync_out
);
logic [1:0] sync_reg;
always_ff @(posedge clk, negedge n_rst)
  if (!n_rst) begin
    sync_out <= 1'b0;
    sync_reg <= 2'b0;
  end
  else begin
    sync_reg <= {sync_reg[0], async_in};
    sync_out <= sync_reg[1];
  end

endmodule
  
//jk flipflop
module jk_ff(
  input logic clk, n_rst, j_in, k_in,
  output logic q_out
);

always_ff @(posedge clk, negedge n_rst)
  if (!n_rst)
    q_out <= 1'b0;
  else if (j_in && k_in)
    q_out <= ~q_out;
  else if (j_in)
    q_out <= 1'b1;
  else if (k_in)
    q_out <= 1'b0;

endmodule

Lab7a/tb.sv

//DO NOT MODIFY THIS FILE. YOU MAY ADD TESTCASES AT THE BOTTOM
//The testbench is a system verilog file that will run tests on what you write in your top module and show the results as a waveform on GTKWave. 
//Testbenches are used for "verification" or check the functional correctness of your circuit.

module lab_testbench ();

logic CLK, N_RST, D_IN, D_OUT; //a testbench has no inputs or outputs, the DUT has.
logic [1023:0] testname;

d_ff u1(.clk(CLK), .n_rst(N_RST), .d_in(D_IN), .d_out(D_OUT)); //create instance of your module and map its inputs and outputs to the tb 

task automatic clock(integer n);
    while (n != 0) begin
        CLK = 1'b1;
        #1;
        CLK = 1'b0;
        #1;
        n--;
    end
endtask //automatic clk generation

initial begin
    $dumpfile ("Lab7a.vcd");
    $dumpvars (0, lab_testbench);
    
    testname="first test with N_RST value 0";
    D_IN = 1'b1; N_RST = 1'b0; CLK = 1'b0;
clock(1);
    #0.25;
    testname="random test1 with N_RST high";
    D_IN = 1'b0; N_RST = 1'b1; CLK=1'b1;
clock(1);
    #0.25;
    testname="random test2 with N_RST high";
    D_IN = 1'b1; N_RST = 1'b1;
clock(1);
    #0.25;
    testname="random test3 with N_RST high";
    D_IN = 1'b0; N_RST = 1'b1;
clock(1);
    #0.25;
   testname="random test4 with N_RST high";
    D_IN = 1'b1; N_RST = 1'b1;
clock(1);
    #0.25;
    testname="random test5 with N_RST high";
    D_IN = 1'b1; N_RST = 1'b1;
clock(1);
    #0.25;
    testname="random test6 with N_RST high";
    D_IN = 1'b0; N_RST = 1'b1;
clock(1);
    #0.25;
   testname="random test7 with N_RST high";
    D_IN = 1'b1; N_RST = 1'b1;
clock(1);

// add your test cases here
end
endmodule

Lab7a/Lab7a.vcd
$date
	Wed Jun  7 09:35:05 2023
$end
$version
	Icarus Verilog
$end
$timescale
	1s
$end
$scope module lab_testbench $end
$var wire 1 ! D_OUT $end
$var reg 1 " CLK $end
$var reg 1 # D_IN $end
$var reg 1 $ N_RST $end
$var reg 1024 % testname [1023:0] $end
$scope module u1 $end
$var wire 1 " clk $end
$var wire 1 # d_in $end
$var wire 1 $ n_rst $end
$var reg 1 ! d_out $end
$upscope $end
$scope task clock $end
$upscope $end
$upscope $end
$enddefinitions $end
$comment Show the parameter values. $end
$dumpall
$end
#0
$dumpvars
b110011001101001011100100111001101110100001000000111010001100101011100110111010000100000011101110110100101110100011010000010000001001110010111110101001001010011010101000010000001110110011000010110110001110101011001010010000000110000 %
0$
1#
1"
0!
$end
#1
0"
#2
1"
1$
0#
b1110010011000010110111001100100011011110110110100100000011101000110010101110011011101000011000100100000011101110110100101110100011010000010000001001110010111110101001001010011010101000010000001101000011010010110011101101000 %
#3
0"
#4
1!
1"
1#
b1110010011000010110111001100100011011110110110100100000011101000110010101110011011101000011001000100000011101110110100101110100011010000010000001001110010111110101001001010011010101000010000001101000011010010110011101101000 %
#5
0"
#6
0!
1"
0#
b1110010011000010110111001100100011011110110110100100000011101000110010101110011011101000011001100100000011101110110100101110100011010000010000001001110010111110101001001010011010101000010000001101000011010010110011101101000 %
#7
0"
#8
1!
1"
1#
b1110010011000010110111001100100011011110110110100100000011101000110010101110011011101000011010000100000011101110110100101110100011010000010000001001110010111110101001001010011010101000010000001101000011010010110011101101000 %
#9
0"
#10
1"
b1110010011000010110111001100100011011110110110100100000011101000110010101110011011101000011010100100000011101110110100101110100011010000010000001001110010111110101001001010011010101000010000001101000011010010110011101101000 %
#11
0"
#12
0!
1"
0#
b1110010011000010110111001100100011011110110110100100000011101000110010101110011011101000011011000100000011101110110100101110100011010000010000001001110010111110101001001010011010101000010000001101000011010010110011101101000 %
#13
0"
#14
1!
1"
1#
b1110010011000010110111001100100011011110110110100100000011101000110010101110011011101000011011100100000011101110110100101110100011010000010000001001110010111110101001001010011010101000010000001101000011010010110011101101000 %
