Lab7b/top.sv
`default_nettype none


module top (
  // I/O ports
  input  logic hz100, reset,
  input  logic [20:0] pb,
  output logic [7:0] left, right,
         ss7, ss6, ss5, ss4, ss3, ss2, ss1, ss0,
  output logic red, green, blue,

  // UART ports
  output logic [7:0] txdata,
  input  logic [7:0] rxdata,
  output logic txclk, rxclk,
  input  logic txready, rxready
);

// Write your code here
  
//task 2
sync_low u2(.clk(hz100), .n_rst(pb[0]), .async_in(pb[1]), .sync_out(right[1]));

  
endmodule

//2-bit synchronizer
module sync_low(
  input logic clk, n_rst, async_in,
  output logic sync_out
);
logic sync_reg;
always_ff @(posedge clk, negedge n_rst)
  if (!n_rst) begin
    sync_out <= 1'b0;
    sync_reg <= 1'b0;
  end
  else begin
    sync_reg <= async_in;
    sync_out <= sync_reg;
  end

endmodule

//synchroflop!

Lab7b/tb.sv

//DO NOT MODIFY THIS FILE. YOU MAY ADD TESTCASES AT THE BOTTOM
//The testbench is a system verilog file that will run tests on what you write in your top module and show the results as a waveform on GTKWave. 
//Testbenches are used for "verification" or check the functional correctness of your circuit.
`timescale 1ms/100us
`default_nettype none

module lab_testbench ();

logic CLK, N_RST, ASYNC_IN, SYNC_OUT; //a testbench has no inputs or outputs, the DUT has.
logic [1023:0] testname;

localparam time CLK_PERIOD = 10; // 100Hz clock

sync_low u1(.clk(CLK), .n_rst(N_RST), .async_in(ASYNC_IN), .sync_out(SYNC_OUT)); //create instance of your module and map its inputs and outputs to the tb 

always begin
    CLK = 1'b0; 
    #(CLK_PERIOD / 2); 
    CLK = 1'b1; 
    #(CLK_PERIOD / 2); 
end



initial begin
    $dumpfile ("Lab7b.vcd");
    $dumpvars(0, lab_testbench);

    testname="first test with N_RST value 0";
    ASYNC_IN = 1'b1; N_RST = 1'b0;
    @(posedge CLK); 
    
    
    testname="random test1 with N_RST high";
    @(negedge CLK); 
    ASYNC_IN = 1'b0; N_RST = 1'b1;
    @(posedge CLK);     

    
    testname="random test2 with N_RST high";
    @(negedge CLK); 
    ASYNC_IN = 1'b1; N_RST = 1'b1;
    @(posedge CLK); 
    
    testname="random test3 with N_RST high";
    @(negedge CLK); 
    ASYNC_IN = 1'b0; N_RST = 1'b1;
    @(posedge CLK); 
    
   testname="random test4 with N_RST high";
   @(negedge CLK); 
    ASYNC_IN = 1'b1; N_RST = 1'b1;
    @(posedge CLK); 
    
    testname="random test5 with N_RST high";
    @(negedge CLK); 
    ASYNC_IN = 1'b1; N_RST = 1'b1;
    @(posedge CLK); 
    

    testname="random test6 with N_RST high";
    @(negedge CLK); 
    ASYNC_IN = 1'b0; N_RST = 1'b1;
    @(posedge CLK); 
    
   testname="random test7 with N_RST high";
   @(negedge CLK);
    ASYNC_IN = 1'b1; N_RST = 1'b1;
    @(posedge CLK); 

    
    $finish; 
// add your test cases here
end
endmodule

Lab7b/Lab7b.vcd
$date
	Wed Jun  7 10:06:36 2023
$end
$version
	Icarus Verilog
$end
$timescale
	100us
$end
$scope module lab_testbench $end
$var wire 1 ! SYNC_OUT $end
$var parameter 64 " CLK_PERIOD $end
$var reg 1 # ASYNC_IN $end
$var reg 1 $ CLK $end
$var reg 1 % N_RST $end
$var reg 1024 & testname [1023:0] $end
$scope module u1 $end
$var wire 1 # async_in $end
$var wire 1 $ clk $end
$var wire 1 % n_rst $end
$var reg 1 ! sync_out $end
$var reg 1 ' sync_reg $end
$upscope $end
$upscope $end
$enddefinitions $end
$comment Show the parameter values. $end
$dumpall
b1010 "
$end
#0
$dumpvars
0'
b110011001101001011100100111001101110100001000000111010001100101011100110111010000100000011101110110100101110100011010000010000001001110010111110101001001010011010101000010000001110110011000010110110001110101011001010010000000110000 &
0%
0$
1#
0!
$end
#50
b1110010011000010110111001100100011011110110110100100000011101000110010101110011011101000011000100100000011101110110100101110100011010000010000001001110010111110101001001010011010101000010000001101000011010010110011101101000 &
1$
#100
1%
0#
0$
#150
b1110010011000010110111001100100011011110110110100100000011101000110010101110011011101000011001000100000011101110110100101110100011010000010000001001110010111110101001001010011010101000010000001101000011010010110011101101000 &
1$
#200
1#
0$
#250
1'
b1110010011000010110111001100100011011110110110100100000011101000110010101110011011101000011001100100000011101110110100101110100011010000010000001001110010111110101001001010011010101000010000001101000011010010110011101101000 &
1$
#300
0#
0$
#350
1!
0'
b1110010011000010110111001100100011011110110110100100000011101000110010101110011011101000011010000100000011101110110100101110100011010000010000001001110010111110101001001010011010101000010000001101000011010010110011101101000 &
1$
#400
1#
0$
#450
0!
1'
b1110010011000010110111001100100011011110110110100100000011101000110010101110011011101000011010100100000011101110110100101110100011010000010000001001110010111110101001001010011010101000010000001101000011010010110011101101000 &
1$
#500
0$
#550
1!
b1110010011000010110111001100100011011110110110100100000011101000110010101110011011101000011011000100000011101110110100101110100011010000010000001001110010111110101001001010011010101000010000001101000011010010110011101101000 &
1$
#600
0#
0$
#650
0'
b1110010011000010110111001100100011011110110110100100000011101000110010101110011011101000011011100100000011101110110100101110100011010000010000001001110010111110101001001010011010101000010000001101000011010010110011101101000 &
1$
#700
1#
0$
#750
0!
1'
1$
